README.rst
bashlint.py
setup.py
bashlint.egg-info/PKG-INFO
bashlint.egg-info/SOURCES.txt
bashlint.egg-info/dependency_links.txt
bashlint.egg-info/entry_points.txt
bashlint.egg-info/not-zip-safe
bashlint.egg-info/top_level.txt