Metadata-Version: 1.1
Name: bashlint
Version: 0.1.0
Summary: Bash linting tool
Home-page: https://github.com/skudriashev/bashlint
Author: Stanislav Kudriashev
Author-email: stas.kudriashev@gmail.com
License: MIT
Download-URL: https://github.com/skudriashev/bashlint/tarball/0.1.0
Keywords: bash
Platform: UNKNOWN
Classifier: Development Status :: 2 - Pre-Alpha
Classifier: Environment :: Console
Classifier: Intended Audience :: Developers
Classifier: License :: OSI Approved :: MIT License
Classifier: Operating System :: OS Independent
Classifier: Programming Language :: Python
Classifier: Programming Language :: Python :: 2
Classifier: Programming Language :: Python :: 2.6
Classifier: Programming Language :: Python :: 2.7
Classifier: Programming Language :: Python :: 3
Classifier: Programming Language :: Python :: 3.3
Classifier: Topic :: Software Development :: Libraries :: Python Modules
